<annotation>
	<folder>photo_ann_test</folder>
	<filename>IMG_8347.JPG</filename>
	<path>IMG_8347.JPG</path>
	<source>
		<database>Unknown</database>
	</source>
	<size>
		<width>1600</width>
		<height>1200</height>
		<depth>3</depth>
	</size>
	<segmented>0</segmented>
	<object>
		<name>hemo</name>
		<pose>Unspecified</pose>
		<truncated>0</truncated>
		<difficult>0</difficult>
		<bndbox>
			<xmin>632</xmin>
			<ymin>1014</ymin>
			<xmax>687</xmax>
			<ymax>1072</ymax>
		</bndbox>
	</object>
	<object>
		<name>hemo</name>
		<pose>Unspecified</pose>
		<truncated>0</truncated>
		<difficult>0</difficult>
		<bndbox>
			<xmin>1106</xmin>
			<ymin>22</ymin>
			<xmax>1165</xmax>
			<ymax>83</ymax>
		</bndbox>
	</object>
	<object>
		<name>hemo</name>
		<pose>Unspecified</pose>
		<truncated>0</truncated>
		<difficult>0</difficult>
		<bndbox>
			<xmin>365</xmin>
			<ymin>379</ymin>
			<xmax>417</xmax>
			<ymax>434</ymax>
		</bndbox>
	</object>
	<object>
		<name>hemo</name>
		<pose>Unspecified</pose>
		<truncated>0</truncated>
		<difficult>0</difficult>
		<bndbox>
			<xmin>867</xmin>
			<ymin>50</ymin>
			<xmax>927</xmax>
			<ymax>110</ymax>
		</bndbox>
	</object>
	<object>
		<name>hemo</name>
		<pose>Unspecified</pose>
		<truncated>0</truncated>
		<difficult>0</difficult>
		<bndbox>
			<xmin>768</xmin>
			<ymin>585</ymin>
			<xmax>823</xmax>
			<ymax>635</ymax>
		</bndbox>
	</object>
	<object>
		<name>hemo</name>
		<pose>Unspecified</pose>
		<truncated>0</truncated>
		<difficult>0</difficult>
		<bndbox>
			<xmin>1211</xmin>
			<ymin>221</ymin>
			<xmax>1265</xmax>
			<ymax>278</ymax>
		</bndbox>
	</object>
</annotation>