<annotation>
	<folder>Photos</folder>
	<filename>IMG_7216.JPG</filename>
	<path>IMG_7216.JPG</path>
	<source>
		<database>Unknown</database>
	</source>
	<size>
		<width>1600</width>
		<height>1200</height>
		<depth>3</depth>
	</size>
	<segmented>0</segmented>
	<object>
		<name>hemo</name>
		<pose>Unspecified</pose>
		<truncated>0</truncated>
		<difficult>0</difficult>
		<bndbox>
			<xmin>371</xmin>
			<ymin>964</ymin>
			<xmax>438</xmax>
			<ymax>1040</ymax>
		</bndbox>
	</object>
	<object>
		<name>hemo</name>
		<pose>Unspecified</pose>
		<truncated>0</truncated>
		<difficult>0</difficult>
		<bndbox>
			<xmin>864</xmin>
			<ymin>1071</ymin>
			<xmax>939</xmax>
			<ymax>1143</ymax>
		</bndbox>
	</object>
	<object>
		<name>hemo</name>
		<pose>Unspecified</pose>
		<truncated>1</truncated>
		<difficult>0</difficult>
		<bndbox>
			<xmin>1187</xmin>
			<ymin>1155</ymin>
			<xmax>1271</xmax>
			<ymax>1200</ymax>
		</bndbox>
	</object>
	<object>
		<name>hemo</name>
		<pose>Unspecified</pose>
		<truncated>1</truncated>
		<difficult>0</difficult>
		<bndbox>
			<xmin>1298</xmin>
			<ymin>1159</ymin>
			<xmax>1382</xmax>
			<ymax>1200</ymax>
		</bndbox>
	</object>
	<object>
		<name>hemo</name>
		<pose>Unspecified</pose>
		<truncated>0</truncated>
		<difficult>0</difficult>
		<bndbox>
			<xmin>741</xmin>
			<ymin>553</ymin>
			<xmax>811</xmax>
			<ymax>623</ymax>
		</bndbox>
	</object>
	<object>
		<name>hemo</name>
		<pose>Unspecified</pose>
		<truncated>0</truncated>
		<difficult>0</difficult>
		<bndbox>
			<xmin>787</xmin>
			<ymin>688</ymin>
			<xmax>866</xmax>
			<ymax>760</ymax>
		</bndbox>
	</object>
	<object>
		<name>hemo</name>
		<pose>Unspecified</pose>
		<truncated>0</truncated>
		<difficult>0</difficult>
		<bndbox>
			<xmin>973</xmin>
			<ymin>524</ymin>
			<xmax>1047</xmax>
			<ymax>590</ymax>
		</bndbox>
	</object>
	<object>
		<name>hemo</name>
		<pose>Unspecified</pose>
		<truncated>0</truncated>
		<difficult>0</difficult>
		<bndbox>
			<xmin>1176</xmin>
			<ymin>93</ymin>
			<xmax>1245</xmax>
			<ymax>161</ymax>
		</bndbox>
	</object>
	<object>
		<name>hemo</name>
		<pose>Unspecified</pose>
		<truncated>0</truncated>
		<difficult>0</difficult>
		<bndbox>
			<xmin>1252</xmin>
			<ymin>548</ymin>
			<xmax>1312</xmax>
			<ymax>609</ymax>
		</bndbox>
	</object>
	<object>
		<name>hemo</name>
		<pose>Unspecified</pose>
		<truncated>0</truncated>
		<difficult>0</difficult>
		<bndbox>
			<xmin>890</xmin>
			<ymin>94</ymin>
			<xmax>949</xmax>
			<ymax>164</ymax>
		</bndbox>
	</object>
</annotation>