<annotation>
	<folder>Photos</folder>
	<filename>IMG_7818.JPG</filename>
	<path>IMG_7818.JPG</path>
	<source>
		<database>Unknown</database>
	</source>
	<size>
		<width>1600</width>
		<height>1200</height>
		<depth>3</depth>
	</size>
	<segmented>0</segmented>
	<object>
		<name>hemo</name>
		<pose>Unspecified</pose>
		<truncated>0</truncated>
		<difficult>0</difficult>
		<bndbox>
			<xmin>1306</xmin>
			<ymin>436</ymin>
			<xmax>1375</xmax>
			<ymax>524</ymax>
		</bndbox>
	</object>
	<object>
		<name>hemo</name>
		<pose>Unspecified</pose>
		<truncated>0</truncated>
		<difficult>0</difficult>
		<bndbox>
			<xmin>1290</xmin>
			<ymin>693</ymin>
			<xmax>1354</xmax>
			<ymax>765</ymax>
		</bndbox>
	</object>
	<object>
		<name>hemo</name>
		<pose>Unspecified</pose>
		<truncated>0</truncated>
		<difficult>0</difficult>
		<bndbox>
			<xmin>1168</xmin>
			<ymin>793</ymin>
			<xmax>1239</xmax>
			<ymax>870</ymax>
		</bndbox>
	</object>
	<object>
		<name>hemo</name>
		<pose>Unspecified</pose>
		<truncated>0</truncated>
		<difficult>0</difficult>
		<bndbox>
			<xmin>797</xmin>
			<ymin>813</ymin>
			<xmax>867</xmax>
			<ymax>879</ymax>
		</bndbox>
	</object>
	<object>
		<name>hemo</name>
		<pose>Unspecified</pose>
		<truncated>0</truncated>
		<difficult>0</difficult>
		<bndbox>
			<xmin>1064</xmin>
			<ymin>933</ymin>
			<xmax>1137</xmax>
			<ymax>1011</ymax>
		</bndbox>
	</object>
	<object>
		<name>hemo</name>
		<pose>Unspecified</pose>
		<truncated>1</truncated>
		<difficult>0</difficult>
		<bndbox>
			<xmin>76</xmin>
			<ymin>1164</ymin>
			<xmax>136</xmax>
			<ymax>1200</ymax>
		</bndbox>
	</object>
	<object>
		<name>hemo</name>
		<pose>Unspecified</pose>
		<truncated>0</truncated>
		<difficult>0</difficult>
		<bndbox>
			<xmin>478</xmin>
			<ymin>1105</ymin>
			<xmax>547</xmax>
			<ymax>1189</ymax>
		</bndbox>
	</object>
	<object>
		<name>hemo</name>
		<pose>Unspecified</pose>
		<truncated>0</truncated>
		<difficult>0</difficult>
		<bndbox>
			<xmin>394</xmin>
			<ymin>896</ymin>
			<xmax>467</xmax>
			<ymax>987</ymax>
		</bndbox>
	</object>
	<object>
		<name>hemo</name>
		<pose>Unspecified</pose>
		<truncated>0</truncated>
		<difficult>0</difficult>
		<bndbox>
			<xmin>413</xmin>
			<ymin>625</ymin>
			<xmax>473</xmax>
			<ymax>692</ymax>
		</bndbox>
	</object>
	<object>
		<name>hemo</name>
		<pose>Unspecified</pose>
		<truncated>0</truncated>
		<difficult>0</difficult>
		<bndbox>
			<xmin>495</xmin>
			<ymin>352</ymin>
			<xmax>576</xmax>
			<ymax>453</ymax>
		</bndbox>
	</object>
	<object>
		<name>hemo</name>
		<pose>Unspecified</pose>
		<truncated>0</truncated>
		<difficult>0</difficult>
		<bndbox>
			<xmin>623</xmin>
			<ymin>254</ymin>
			<xmax>688</xmax>
			<ymax>321</ymax>
		</bndbox>
	</object>
	<object>
		<name>hemo</name>
		<pose>Unspecified</pose>
		<truncated>0</truncated>
		<difficult>0</difficult>
		<bndbox>
			<xmin>1086</xmin>
			<ymin>842</ymin>
			<xmax>1139</xmax>
			<ymax>898</ymax>
		</bndbox>
	</object>
	<object>
		<name>hemo</name>
		<pose>Unspecified</pose>
		<truncated>0</truncated>
		<difficult>0</difficult>
		<bndbox>
			<xmin>1415</xmin>
			<ymin>9</ymin>
			<xmax>1494</xmax>
			<ymax>87</ymax>
		</bndbox>
	</object>
	<object>
		<name>hemo</name>
		<pose>Unspecified</pose>
		<truncated>0</truncated>
		<difficult>0</difficult>
		<bndbox>
			<xmin>1458</xmin>
			<ymin>47</ymin>
			<xmax>1533</xmax>
			<ymax>120</ymax>
		</bndbox>
	</object>
</annotation>